README.rst
setup.cfg
setup.py
scikit_gof.egg-info/PKG-INFO
scikit_gof.egg-info/SOURCES.txt
scikit_gof.egg-info/dependency_links.txt
scikit_gof.egg-info/requires.txt
scikit_gof.egg-info/top_level.txt
skgof/__init__.py
skgof/addist.py
skgof/cvmdist.py
skgof/ecdfgof.py
skgof/ksdist.py
skgof/testsim.py
skgof/vect.py