Metadata-Version: 1.1
Name: scikit-gof
Version: 0.0.2
Summary: Variations on goodness of fit tests for SciPy.
Home-page: http://github.org/wrwrwr/scikit-gof
Author: Wojciech Ruszczewski
Author-email: scipy@wr.waw.pl
License: MIT
Platform: UNKNOWN
Classifier: Development Status :: 3 - Alpha
Classifier: Intended Audience :: Science/Research
Classifier: Topic :: Scientific/Engineering :: Information Analysis
Classifier: License :: OSI Approved :: MIT License
Classifier: Programming Language :: Python :: 3.4
